{
	"global":"global.less",
	"ux-defaults":"ux-defaults.less",
	"ux-grid-system":"ux-grid-system.less",
	"ux-media-queries":"ux-media-queries.less",
	"ux-page-contents":"ux-page-contents.less",
	"ux-print": "ux-print.less",
	"ux-structure":"ux-structure.less",
	"ux-tables":"ux-tables.less",
	"ux-utility":"ux-utility.less",
	"app-defaults":"app-defaults.less",
	"global-print":"global-print.less",
	"gsa-defaults":"gsa-defaults.less",
	"lazy-ckeditor-override":"lazy-ckeditor-override.less",
	"lazy-dynatree":"lazy-dynatree.less",
	"lazy-fullcalendar-overrides":"lazy-fullcalendar-overrides.less",
	"lazy-fullcalendar":"lazy-fullcalendar.less",
	"lazy-jquery-page-feedback":"lazy-jquery-page-feedback.less",
	"lazy-jquery-qtip": "lazy-jquery-qtip.less",
	"lazy-jquery-ui-overrides": "lazy-jquery-ui-overrides.less",
	"lazy-jquery-ui": "lazy-jquery-ui.less",
	"lazy-jquery.chosen-overrides": "lazy-jquery.chosen-overrides.less",
	"lazy-jquery.chosen": "lazy-jquery.chosen.less",
	"lazy-jquery.expander": "lazy-jquery.expander.less",
	"lazy-jquery.joyride": "lazy-jquery.joyride.less",
	"lazy-jquery.open-ux.character-counter-overrides": "lazy-jquery.open-ux.character-counter-overrides.less",
	"lazy-jquery.open-ux.form-enhancements": "lazy-jquery.open-ux.form-enhancements.less",
	"lazy-jquery.open-ux.keyboard-shortcuts": "lazy-jquery.open-ux.keyboard-shortcuts.less",
	"lazy-jquery.open-ux.navigational-warning": "lazy-jquery.open-ux.navigational-warning.less",
	"lazy-jquery.open-ux.notifications": "lazy-jquery.open-ux.notifications.less",
	"lazy-jquery.open-ux.popovers": "lazy-jquery.open-ux.popovers.less",
	"lazy-jquery.validationEngine-overrides": "lazy-jquery.validationEngine-overrides",
	"lazy-jquery.validationEngine": "lazy-jquery.validationEngine.less",
	"lazy-video-js": "lazy-video-js.less",
	"website": "website.less"
}